Metadata-Version: 2.1
Name: aqtest1
Version: 0.7.2
Summary: please install samtools and minimap2 from bioconda(anaconda) in advance
Home-page: UNKNOWN
Author: HENRY TEST
Author-email: liuyichen@std.uestc.edu.cn
License: UNKNOWN
Platform: UNKNOWN
Requires-Dist: pysam
Requires-Dist: numpy
Requires-Dist: scipy
